MedatechUK/__init__.py
MedatechUK/Landlord/Icons.py
MedatechUK/Landlord/UI.py
MedatechUK/Landlord/__init__.py
MedatechUK/Landlord/label.py
MedatechUK/Landlord/files/LabelSpec.py
MedatechUK/Landlord/files/settings.ini
MedatechUK/Landlord/files/undercon.pdf
MedatechUK.Landlord-0.0.18.dist-info/METADATA
MedatechUK.Landlord-0.0.18.dist-info/WHEEL
MedatechUK.Landlord-0.0.18.dist-info/licence
MedatechUK.Landlord-0.0.18.dist-info/top_level.txt
MedatechUK.Landlord-0.0.18.dist-info/RECORD
